langchain_litellm/__init__.py
langchain_litellm/chat_models/__init__.py
langchain_litellm/chat_models/litellm.py
langchain_litellm/chat_models/litellm_router.py
langchain_litellm/py.typed
langchain_litellm-0.3.4.dist-info/METADATA
langchain_litellm-0.3.4.dist-info/WHEEL
langchain_litellm-0.3.4.dist-info/licenses/LICENSE
langchain_litellm-0.3.4.dist-info/RECORD
