Metadata-Version: 2.4
Name: langchain-litellm
Version: 0.3.4
Summary: An integration package connecting Litellm and LangChain
License: MIT
License-File: LICENSE
Author: Akshay Dongare
Requires-Python: >=3.10,<4.0
Classifier: License :: OSI Approved :: MIT License
Classifier: Programming Language :: Python :: 3
Classifier: Programming Language :: Python :: 3.10
Classifier: Programming Language :: Python :: 3.11
Classifier: Programming Language :: Python :: 3.12
Classifier: Programming Language :: Python :: 3.13
Classifier: Programming Language :: Python :: 3.14
Requires-Dist: langchain-core (>0.3.15,<2.0.0)
Requires-Dist: litellm (>=1.65.1,<2.0.0)
Project-URL: Repository, https://github.com/langchain-ai/langchain/blob/master/docs/docs/integrations/chat/litellm.ipynb
Project-URL: Release Notes, https://github.com/langchain-ai/langchain/blob/master/docs/docs/integrations/providers/litellm.mdx
Project-URL: Source Code, https://github.com/Akshay-Dongare/langchain-litellm
